README.rst
setup.py
function_trace/__init__.py
function_trace/old.py
function_trace/test.py
function_trace.egg-info/PKG-INFO
function_trace.egg-info/SOURCES.txt
function_trace.egg-info/dependency_links.txt
function_trace.egg-info/top_level.txt