Metadata-Version: 1.0
Name: function-trace
Version: 1.1.0
Summary: Hierarchical trace of function/method call arguments and return values
Home-page: https://github.com/RedHatQE/function_trace
Author: Jeff Weiss
Author-email: jweiss@redhat.com
License: PSF
Keywords: trace debugging
Platform: UNKNOWN
